LICENSE.md
MANIFEST.in
README.md
setup.py
gitpylib/__init__.py
gitpylib/branch.py
gitpylib/common.py
gitpylib/config.py
gitpylib/file.py
gitpylib/hook.py
gitpylib/log.py
gitpylib/remote.py
gitpylib/repo.py
gitpylib/stash.py
gitpylib/status.py
gitpylib/sync.py
gitpylib.egg-info/PKG-INFO
gitpylib.egg-info/SOURCES.txt
gitpylib.egg-info/dependency_links.txt
gitpylib.egg-info/top_level.txt